{
  "$schema": "http://json-schema.org/draft-04/schema",
  "title": "DATS dataset distribution schema",
  "description": "(From DCAT) Represents a specific available form of a dataset. Each dataset might be available in different forms, these forms might represent different formats of the dataset or different endpoints. Examples of distributions include a downloadable CSV file, an API or an RSS feed.",
  "type": "object",
  "properties": {
    "identifiers": {
      "description": "Primary identifiers for the dataset distribution.",
      "type": "array",
      "items": {
        "$ref": "identifier_info_schema.json#"
      }
    },
    "alternateIdentifiers": {
      "description": "Alternate identifiers for the dataset distribution.",
      "type": "array",
      "items": {
        "$ref": "alternate_identifier_info_schema.json#"
      }
    },
    "relatedIdentifiers": {
      "description": "Related identifiers for the dataset distribution.",
      "type": "array",
      "items": {
        "$ref": "related_identifier_info_schema.json#"
      }
    },
    "storedIn" : {
      "description": "The data repository(ies) hosting the dataset.",
      "type" : "array",
      "items" : {
        "$ref": "data_repository_schema.json#"
      }
    },
    "dates" : {
      "description": "Relevant dates for the datasets, a date must be added, e.g. creation date or last modification date should be added.",
      "type" : "array",
      "items" : {
        "$ref" : "date_info_schema.json#"
      },
      "minItems": 1
    },
    "version" : {
      "description": "A release point for the dataset when applicable.",
      "type" : "string"
    },
    "accessModalities" : {
      "description": "The information about access modality for the dataset.",
      "type" : "array",
      "items" : {
        "$ref" : "access_schema.json#"
      },
      "minItems": 1
    },
    "curationStatus": {
      "description": "The level of curation of the dataset distribution.",
      "type": "array",
      "items": {
        "$ref": "annotation_schema.json#"
      }
    },
    "conformsTo" : {
      "description": "A data standard whose requirements and constraints are met by the dataset.",
      "type" : "array",
      "items" : {
        "$ref": "data_standard_schema.json#"
      }
    },
    "size": {
      "description": "The size of the dataset.",
      "type": "number"
    },
    "unit": {
      "description": "The unit of measurement used to estimate the size of the dataset (e.g, petabyte). Ideally, the unit should be coming from a reference controlled terminology.",
      "$ref": "annotation_schema.json#"
    }
  },
  "additionalProperties": false,
  "required": [ "dates" ]
}
