{
  "$schema": "http://json-schema.org/draft-04/schema",
  "title": "DATS data analysis schema",
  "description": "Process (or activity) of transforming data and producing data.",
  "type": "object",
  "properties": {
    "identifiers": {
      "description": "Primary identifiers for the activity.",
      "type": "array",
      "items": {
        "$ref": "identifier_info_schema.json#"
      }
    },
    "alternateIdentifiers": {
      "description": "Alternate identifiers for the activity.",
      "type": "array",
      "items": {
        "$ref": "alternate_identifier_info_schema.json#"
      }
    },
    "relatedIdentifiers": {
      "description": "Related identifiers for the activity.",
      "type": "array",
      "items": {
        "$ref": "related_identifier_info_schema.json#"
      }
    },
    "name": {
      "description": "The name of the activity, usually one sentece or short description of the activity.",
      "type" :  "string"
    },
    "startDate": {
      "description": "A timestamp to record the starting point of the activity.",
      "$ref": "date_info_schema.json#"
    },
    "endDate": {
      "description": "A timestamp to record the end point of the activity.",
      "$ref": "date_info_schema.json#"
    },
    "duration": {
      "description": "The time during which the activity takes place.",
      "type" :  "string"
    },
    "location" : {
      "description": "The location where the activity takes place.",
      "oneOf": [
        {
          "type": "string"
        },
        {
          "type": "string",
          "format" : "uri"
        }
      ]
    },
    "performedBy" : {
      "description": "The person(s) or organisation(s) responsible for executing the process.",
      "type" : "array",
      "items" : {
        "anyOf": [
          {"$ref" : "person_schema.json#"},
          {"$ref" : "organization_schema.json#"}
        ]
      }
    }
  },
  "keywords": {
    "description": "Tags associated with the activity, which will help in its discovery.",
    "type": "array",
    "items": {
      "oneOf": [
        {
          "type": "string"
        },
        {
          "type": "string",
          "format" : "uri"
        }
      ]
    }
  },
  "input" : {
    "description": "The entities used as input.",
    "type": "array",
    "items":{
        "$ref" : "dataset_schema.json#"
    },
    "minItems": 1
  },
  "output" : {
    "description": "The entities resulting from applying the activity.",
    "type": "array",
    "items":{
        "$ref" : "dataset_schema.json#"
    },
    "minItems": 1
  },
  "required": [ "name", "input", "output" ]
}